github/__init__.py
github_io-0.0.1.dist-info/licenses/LICENSE
github_io-0.0.1.dist-info/METADATA
github_io-0.0.1.dist-info/WHEEL
github_io-0.0.1.dist-info/top_level.txt
github_io-0.0.1.dist-info/RECORD
