Metadata-Version: 2.4
Name: github.io
Version: 0.0.1
Summary: An asynchronous python wrapper around the GitHub API
Author-email: VarMonke <var.monke@gmail.com>
License-Expression: MIT
Project-URL: Homepage, https://github.com/VarMonke/Github-API-Wrapper
Project-URL: Issues, https://github.com/VarMonke/Github-API-Wrapper/issues
Classifier: Programming Language :: Python :: 3
Classifier: Operating System :: OS Independent
Requires-Python: >=3.8
License-File: LICENSE
Dynamic: license-file
